bottlepratchett.py
botttlepratchett-1.0.0.dist-info/METADATA
botttlepratchett-1.0.0.dist-info/WHEEL
botttlepratchett-1.0.0.dist-info/top_level.txt
botttlepratchett-1.0.0.dist-info/RECORD
