Metadata-Version: 2.1
Name: botttlepratchett
Version: 1.0.0
Summary: A middleware for Bottle that provides GNU Terry Pratchett
Home-page: https://git.sr.ht/~shakna/bottlepratchett
Author: James Milne
Author-email: james.milne@protonmail.com
License: UNKNOWN
Platform: UNKNOWN
Classifier: Programming Language :: Python :: 3
Classifier: License :: OSI Approved :: BSD License
Classifier: Operating System :: OS Independent
Requires-Dist: bottle (>=0.12.1)
